pspman/.psprintrc.yml
pspman/__init__.py
pspman/__main__.py
pspman/actions.py
pspman/classes.py
pspman/define.py
pspman/errors.py
pspman/installations.py
pspman/project_actions.py
pspman/queues.py
pspman/shell.py
pspman/tag.py
pspman/tools.py
pspman-21.3.13.dist-info/LICENSE
pspman-21.3.13.dist-info/METADATA
pspman-21.3.13.dist-info/WHEEL
pspman-21.3.13.dist-info/entry_points.txt
pspman-21.3.13.dist-info/top_level.txt
pspman-21.3.13.dist-info/RECORD
