Metadata-Version: 2.1
Name: pspman
Version: 21.3.13
Summary: Personal Simple Package Manager
Home-page: https://github.com/pradyparanjpe/pspman
Author: Pradyumna Paranjape
Author-email: pradyparanjpe@rediffmail.com
License: LGPLv3
Platform: linux
Requires-Python: >=3.7
Requires-Dist: psprint
Requires-Dist: argcomplete
